Metadata-Version: 1.0
Name: xgbm
Version: 0.0.1
Summary: eXplainable Gradient Boosting Models
Home-page: https://github.com/firmai/xgbm
Author: snowde
Author-email: d.snow@firmai.org
License: MIT
Platform: UNKNOWN
